pysmps/__init__.py
pysmps/smps_loader.py
pysmps-1.5.6.dist-info/LICENSE
pysmps-1.5.6.dist-info/METADATA
pysmps-1.5.6.dist-info/WHEEL
pysmps-1.5.6.dist-info/top_level.txt
pysmps-1.5.6.dist-info/RECORD
