Metadata-Version: 2.1
Name: pysmps
Version: 1.5.6
Summary: Utilities for parsing MPS and SMPS file formats.
Home-page: https://github.com/jmaerte/pysmps
Author: Julian Maerte
Author-email: maertej@students.uni-marburg.de
License: UNKNOWN
Platform: UNKNOWN
